dynalite_panel/__init__.py
dynalite_panel/constants.py
dynalite_panel/entrypoint-94572d1e.js
dynalite_panel/entrypoint-94572d1e.js.gz
dynalite_panel/frontend_es5/0176177f.js
dynalite_panel/frontend_es5/0176177f.js.gz
dynalite_panel/frontend_es5/280bd5a8.js
dynalite_panel/frontend_es5/280bd5a8.js.LICENSE.txt
dynalite_panel/frontend_es5/280bd5a8.js.gz
dynalite_panel/frontend_es5/28deee2e.js
dynalite_panel/frontend_es5/28deee2e.js.gz
dynalite_panel/frontend_es5/3934967e.js
dynalite_panel/frontend_es5/3934967e.js.LICENSE.txt
dynalite_panel/frontend_es5/3934967e.js.gz
dynalite_panel/frontend_es5/544a6346.js
dynalite_panel/frontend_es5/544a6346.js.LICENSE.txt
dynalite_panel/frontend_es5/544a6346.js.gz
dynalite_panel/frontend_es5/549f5f17.js
dynalite_panel/frontend_es5/549f5f17.js.LICENSE.txt
dynalite_panel/frontend_es5/549f5f17.js.gz
dynalite_panel/frontend_es5/59e04dd8.js
dynalite_panel/frontend_es5/59e04dd8.js.gz
dynalite_panel/frontend_es5/6914a402.js
dynalite_panel/frontend_es5/6914a402.js.LICENSE.txt
dynalite_panel/frontend_es5/6914a402.js.gz
dynalite_panel/frontend_es5/7cba2f88.js
dynalite_panel/frontend_es5/7cba2f88.js.LICENSE.txt
dynalite_panel/frontend_es5/7cba2f88.js.gz
dynalite_panel/frontend_es5/8081cb55.js
dynalite_panel/frontend_es5/8081cb55.js.gz
dynalite_panel/frontend_es5/811ccb02.js
dynalite_panel/frontend_es5/811ccb02.js.gz
dynalite_panel/frontend_es5/8ddbc98a.js
dynalite_panel/frontend_es5/8ddbc98a.js.LICENSE.txt
dynalite_panel/frontend_es5/8ddbc98a.js.gz
dynalite_panel/frontend_es5/9096b401.js
dynalite_panel/frontend_es5/9096b401.js.LICENSE.txt
dynalite_panel/frontend_es5/9096b401.js.gz
dynalite_panel/frontend_es5/a0807cba.js
dynalite_panel/frontend_es5/a0807cba.js.gz
dynalite_panel/frontend_es5/b01dfb96.js
dynalite_panel/frontend_es5/b01dfb96.js.LICENSE.txt
dynalite_panel/frontend_es5/b01dfb96.js.gz
dynalite_panel/frontend_es5/cd7b8f7d.js
dynalite_panel/frontend_es5/cd7b8f7d.js.LICENSE.txt
dynalite_panel/frontend_es5/cd7b8f7d.js.gz
dynalite_panel-0.0.3.dist-info/LICENSE
dynalite_panel-0.0.3.dist-info/METADATA
dynalite_panel-0.0.3.dist-info/WHEEL
dynalite_panel-0.0.3.dist-info/top_level.txt
dynalite_panel-0.0.3.dist-info/RECORD
